poster_to_markdown/__init__.py
poster_to_markdown/cli.py
poster_to_markdown/prompts.py
poster_to_markdown/tools/arxiv_search.py
poster_to_markdown-0.1.0.dist-info/METADATA
poster_to_markdown-0.1.0.dist-info/WHEEL
poster_to_markdown-0.1.0.dist-info/entry_points.txt
poster_to_markdown-0.1.0.dist-info/licenses/LICENSE
poster_to_markdown-0.1.0.dist-info/RECORD
