Metadata-Version: 2.4
Name: poster-to-markdown
Version: 0.1.0
Summary: Convert research posters to markdown summaries using OpenAI
Author-email: Seung Hyun Kim <skim0119@gmail.com>
License-File: LICENSE
Requires-Python: >=3.10
Requires-Dist: arxiv>=2.2.0
Requires-Dist: asyncio>=3.4.3
Requires-Dist: click
Requires-Dist: mcp[cli]>=1.9.1
Requires-Dist: openai
Requires-Dist: pillow
Requires-Dist: pillow-heif
Requires-Dist: python-dateutil
